hygiene/__init__.py
hygiene/py.typed
module_hygiene-0.3.4.dist-info/METADATA
module_hygiene-0.3.4.dist-info/WHEEL
module_hygiene-0.3.4.dist-info/licenses/AUTHORS.md
module_hygiene-0.3.4.dist-info/licenses/LICENSE
module_hygiene-0.3.4.dist-info/RECORD
