Metadata-Version: 2.1
Name: module-hygiene
Version: 0.3.4
Summary: Keep your Python modules (and packages, and any other namespaces) clean and tidy!
Project-URL: Documentation, https://github.com/cadojo/module-hygiene#readme
Project-URL: Issues, https://github.com/cadojo/module-hygiene/issues
Project-URL: Source, https://github.com/cadojo/module-hygiene
Author-email: Joe Carpinelli <jdcarpinelli@gmail.com>
License-Expression: MIT
License-File: AUTHORS.md
License-File: LICENSE
Keywords: hygiene,module,namespace
Classifier: Development Status :: 4 - Beta
Classifier: Programming Language :: Python
Classifier: Programming Language :: Python :: 3.7
Classifier: Programming Language :: Python :: 3.8
Classifier: Programming Language :: Python :: 3.9
Classifier: Programming Language :: Python :: 3.10
Classifier: Programming Language :: Python :: 3.11
Classifier: Programming Language :: Python :: Implementation :: CPython
Classifier: Programming Language :: Python :: Implementation :: PyPy
Classifier: Typing :: Typed
Requires-Python: >=3.8
